{
  "changelog": [
    {
      "ChangeList": [
        {
          "Id": "bf84f9b9-7809-48b4-aeeb-4db380be2b4b",
          "ApiChange": "Resource",
          "ChangedApiName": "changeNotification",
          "ChangeType": "Deprecation",
          "Description": "Authenticating Event Hubs by using shared access signatures (SAS) will be deprecated soon. To subscribe to [Microsoft Graph change notifications via Azure Event Hubs](https://learn.microsoft.com/en-us/graph/change-notifications-delivery-event-hubs), we recommend using Microsoft Entra ID role-based access control (RBAC) instead. Follow the [guidance to migrate to RBAC](https://learn.microsoft.com/en-us/graph/change-notifications-delivery-event-hubs#migrate-an-event-hub-authentication-to-microsoft-entra-id-rbac).",
          "Target": "changeNotification"
        }
      ],
      "Id": "bf84f9b9-7809-48b4-aeeb-4db380be2b4b",
      "Cloud": "prd",
      "Version": "v1.0",
      "CreatedDateTime": "2024-09-19T00:00:00",
      "WorkloadArea": "Change notifications",
      "SubArea": ""
    },
    {
      "ChangeList": [
        {
          "Id": "342387cd-2f3a-4d5f-8cc8-2d3350000a54",
          "ApiChange": "Resource",
          "ChangedApiName": "application",
          "ChangeType": "Addition",
          "Description": "Added the Microsoft Graph Bicep resource for deploying the [application](https://learn.microsoft.com/en-us/graph/api/resources/application?view=graph-rest-1.0) resource type using Bicep templates for Microsoft Graph resources in infrastructure-as-code (IaC) scenarios. For more information, see [Bicep templates for Microsoft Graph resources](https://aka.ms/graphbicep).",
          "Target": "application"
        }
      ],
      "Id": "342387cd-2f3a-4d5f-8cc8-2d3350000a54",
      "Cloud": "Prod",
      "Version": "v1.0",
      "CreatedDateTime": "2024-05-21T00:00:00.5014179Z",
      "WorkloadArea": "Applications",
      "SubArea": ""
    },
    {
      "ChangeList": [
        {
          "Id": "342387cd-2f3a-4d5f-8cc8-2d3350000a54",
          "ApiChange": "Resource",
          "ChangedApiName": "federatedIdentityCredential",
          "ChangeType": "Addition",
          "Description": "Added the Microsoft Graph Bicep resource for deploying the [federatedIdentityCredential](https://learn.microsoft.com/en-us/graph/api/resources/federatedIdentityCredential?view=graph-rest-1.0) resource type using Bicep templates for Microsoft Graph resources in infrastructure-as-code (IaC) scenarios. For more information, see [Bicep templates for Microsoft Graph resources](https://aka.ms/graphbicep).",
          "Target": "federatedIdentityCredential"
        }
      ],
      "Id": "342387cd-2f3a-4d5f-8cc8-2d3350000a54",
      "Cloud": "Prod",
      "Version": "v1.0",
      "CreatedDateTime": "2024-05-21T00:00:00.5014179Z",
      "WorkloadArea": "Applications",
      "SubArea": ""
    },
    {
      "ChangeList": [
        {
          "Id": "342387cd-2f3a-4d5f-8cc8-2d3350000a54",
          "ApiChange": "Resource",
          "ChangedApiName": "servicePrincipal",
          "ChangeType": "Addition",
          "Description": "Added the Microsoft Graph Bicep resource for deploying the [servicePrincipal](https://learn.microsoft.com/en-us/graph/api/resources/servicePrincipal?view=graph-rest-1.0) resource type using Bicep templates for Microsoft Graph resources in infrastructure-as-code (IaC) scenarios. For more information, see [Bicep templates for Microsoft Graph resources](https://aka.ms/graphbicep).",
          "Target": "servicePrincipal"
        }
      ],
      "Id": "342387cd-2f3a-4d5f-8cc8-2d3350000a54",
      "Cloud": "Prod",
      "Version": "v1.0",
      "CreatedDateTime": "2024-05-21T00:00:00.5014179Z",
      "WorkloadArea": "Applications",
      "SubArea": ""
    },
    {
      "ChangeList": [
        {
          "Id": "342387cd-2f3a-4d5f-8cc8-2d3350000a54",
          "ApiChange": "Resource",
          "ChangedApiName": "oAuth2PermissionGrant",
          "ChangeType": "Addition",
          "Description": "Added the Microsoft Graph Bicep resource for deploying the [oAuth2PermissionGrant](https://learn.microsoft.com/en-us/graph/api/resources/oAuth2PermissionGrant?view=graph-rest-1.0) resource type using Bicep templates for Microsoft Graph resources in infrastructure-as-code (IaC) scenarios. For more information, see [Bicep templates for Microsoft Graph resources](https://aka.ms/graphbicep).",
          "Target": "oAuth2PermissionGrant"
        }
      ],
      "Id": "342387cd-2f3a-4d5f-8cc8-2d3350000a54",
      "Cloud": "Prod",
      "Version": "v1.0",
      "CreatedDateTime": "2024-05-21T00:00:00.5014179Z",
      "WorkloadArea": "Applications",
      "SubArea": ""
    },
    {
      "ChangeList": [
        {
          "Id": "342387cd-2f3a-4d5f-8cc8-2d3350000a54",
          "ApiChange": "Resource",
          "ChangedApiName": "appRoleAssignedTo",
          "ChangeType": "Addition",
          "Description": "Added the Microsoft Graph Bicep resource for deploying the [appRoleAssignment](https://learn.microsoft.com/en-us/graph/api/resources/appRoleAssignment?view=graph-rest-1.0) resource type using Bicep templates for Microsoft Graph resources in infrastructure-as-code (IaC) scenarios. For more information, see [Bicep templates for Microsoft Graph resources](https://aka.ms/graphbicep).",
          "Target": "appRoleAssignment"
        }
      ],
      "Id": "342387cd-2f3a-4d5f-8cc8-2d3350000a54",
      "Cloud": "Prod",
      "Version": "v1.0",
      "CreatedDateTime": "2024-05-21T00:00:00.5014179Z",
      "WorkloadArea": "Applications",
      "SubArea": ""
    },
    {
      "ChangeList": [
        {
          "Id": "342387cd-2f3a-4d5f-8cc8-2d3350000a54",
          "ApiChange": "Resource",
          "ChangedApiName": "group",
          "ChangeType": "Addition",
          "Description": "Added the Microsoft Graph Bicep resource for deploying the [group](https://learn.microsoft.com/en-us/graph/api/resources/group?view=graph-rest-1.0) resource type using Bicep templates for Microsoft Graph resources in infrastructure-as-code (IaC) scenarios. For more information, see [Bicep templates for Microsoft Graph resources](https://aka.ms/graphbicep).",
          "Target": "group"
        }
      ],
      "Id": "342387cd-2f3a-4d5f-8cc8-2d3350000a54",
      "Cloud": "Prod",
      "Version": "v1.0",
      "CreatedDateTime": "2024-05-21T00:00:00.5014179Z",
      "WorkloadArea": "Groups",
      "SubArea": ""
    },
    {
      "ChangeList": [
        {
          "Id": "0a01c9dd-93ec-4529-875e-842a925277d1",
          "ApiChange": "Resource",
          "ChangedApiName": "ediscoveryCase,reviewSet,reviewSetQuery",
          "ChangeType": "Addition",
          "Description": "Introduced the compliance eDiscovery API, including the [ediscoveryCase](https://learn.microsoft.com/en-us/graph/api/resources/security-ediscoverycase?view=graph-rest-beta), [reviewSet](https://learn.microsoft.com/en-us/graph/api/resources/security-ediscoveryreviewset?view=graph-rest-beta), and [reviewSetQuery](https://docs.microsoft.com/en-us/graph/api/resources/security-ediscoveryreviewsetquery?view=graph-rest-beta), and operations.",
          "Target": "ediscoveryCase,reviewSet,reviewSetQuery"
        }
      ],
      "Id": "0a01c9dd-93ec-4529-875e-842a925277d1",
      "Cloud": "prd",
      "Version": "beta",
      "CreatedDateTime": "2020-07-01T00:00:00",
      "WorkloadArea": "Compliance ",
      "SubArea": "eDiscovery"
    },
    {
      "ChangeList": [
        {
          "Id": "13bdd50b-5817-4a82-a7c9-730696cebdfc",
          "ApiChange": "Resource",
          "ChangedApiName": "schema extensions,Microsoft Cloud for US Government",
          "ChangeType": "Addition",
          "Description": "The [schema extensions](https://docs.microsoft.com/en-us/graph/api/resources/schemaextension) feature is now generally available in [Microsoft Cloud for US Government](https://docs.microsoft.com/en-us/graph/deployments).",
          "Target": "schema extensions,Microsoft Cloud for US Government"
        }
      ],
      "Id": "13bdd50b-5817-4a82-a7c9-730696cebdfc",
      "Cloud": "prd",
      "Version": "v1.0",
      "CreatedDateTime": "2020-07-01T00:00:00",
      "WorkloadArea": "Extensions ",
      "SubArea": "Schema extensions"
    }
  ]
}
