{
    "changelog": [
        {
            "ChangeList": [
                {
                    "Id": "b2911b20-27e1-11ec-9ce8-b357a2761d24",
                    "ApiChange": "Relationship",
                    "ChangedApiName": "customSecurityAttributeDefinitions",
                    "ChangeType": "Addition",
                    "Description": "Added the **customSecurityAttributeDefinitions** relationship to the [directory](https://docs.microsoft.com/en-us/graph/api/resources/directory?view=graph-rest-beta) resource.",
                    "Target": "directory"
                },
                {
                    "Id": "b2937e69-27e1-11ec-9ce8-b357a2761d24",
                    "ApiChange": "Relationship",
                    "ChangedApiName": "attributeSets",
                    "ChangeType": "Addition",
                    "Description": "Added the **attributeSets** relationship to the [directory](https://docs.microsoft.com/en-us/graph/api/resources/directory?view=graph-rest-beta) resource.",
                    "Target": "directory"
                },
                {
                    "Id": "b295decc-27e1-11ec-9ce8-b357a2761d24",
                    "ApiChange": "Relationship",
                    "ChangedApiName": "inboundSharedUserProfiles",
                    "ChangeType": "Addition",
                    "Description": "Added the **inboundSharedUserProfiles** relationship to the [directory](https://docs.microsoft.com/en-us/graph/api/resources/directory?view=graph-rest-beta) resource.",
                    "Target": "directory"
                },
                {
                    "Id": "b2984505-27e1-11ec-9ce8-b357a2761d24",
                    "ApiChange": "Relationship",
                    "ChangedApiName": "outboundSharedUserProfiles",
                    "ChangeType": "Addition",
                    "Description": "Added the **outboundSharedUserProfiles** relationship to the [directory](https://docs.microsoft.com/en-us/graph/api/resources/directory?view=graph-rest-beta) resource.",
                    "Target": "directory"
                },
                {
                    "Id": "b2adb90d-27e1-11ec-9ce8-b357a2761d24",
                    "ApiChange": "Resource",
                    "ChangedApiName": "attributeSet",
                    "ChangeType": "Addition",
                    "Description": "Added the [attributeSet](https://docs.microsoft.com/en-us/graph/api/resources/attributeSet?view=graph-rest-beta) resource type.",
                    "Target": "attributeSet"
                },
                {
                    "Id": "b2b018bb-27e1-11ec-9ce8-b357a2761d24",
                    "ApiChange": "Resource",
                    "ChangedApiName": "customSecurityAttributeDefinition",
                    "ChangeType": "Addition",
                    "Description": "Added the [customSecurityAttributeDefinition](https://docs.microsoft.com/en-us/graph/api/resources/customSecurityAttributeDefinition?view=graph-rest-beta) resource type.",
                    "Target": "customSecurityAttributeDefinition"
                },
                {
                    "Id": "b2b27b6b-27e1-11ec-9ce8-b357a2761d24",
                    "ApiChange": "Resource",
                    "ChangedApiName": "allowedValue",
                    "ChangeType": "Addition",
                    "Description": "Added the [allowedValue](https://docs.microsoft.com/en-us/graph/api/resources/allowedValue?view=graph-rest-beta) resource type.",
                    "Target": "allowedValue"
                },
                {
                    "Id": "b2b4db9d-27e1-11ec-9ce8-b357a2761d24",
                    "ApiChange": "Property",
                    "ChangedApiName": "customSecurityAttributes",
                    "ChangeType": "Addition",
                    "Description": "Added the **customSecurityAttributes** property to the [device](https://docs.microsoft.com/en-us/graph/api/resources/device?view=graph-rest-beta) resource.",
                    "Target": "device"
                },
                {
                    "Id": "b2b73f69-27e1-11ec-9ce8-b357a2761d24",
                    "ApiChange": "Property",
                    "ChangedApiName": "isManagementRestricted",
                    "ChangeType": "Addition",
                    "Description": "Added the **isManagementRestricted** property to the [device](https://docs.microsoft.com/en-us/graph/api/resources/device?view=graph-rest-beta) resource.",
                    "Target": "device"
                },
                {
                    "Id": "b2bac1ef-27e1-11ec-9ce8-b357a2761d24",
                    "ApiChange": "Property",
                    "ChangedApiName": "createdDateTime",
                    "ChangeType": "Addition",
                    "Description": "Added the **createdDateTime** property to the [device](https://docs.microsoft.com/en-us/graph/api/resources/device?view=graph-rest-beta) resource.",
                    "Target": "device"
                },
                {
                    "Id": "b2bd2617-27e1-11ec-9ce8-b357a2761d24",
                    "ApiChange": "Resource",
                    "ChangedApiName": "privateEndpointConnection",
                    "ChangeType": "Addition",
                    "Description": "Added the [privateEndpointConnection](https://docs.microsoft.com/en-us/graph/api/resources/privateEndpointConnection?view=graph-rest-beta) resource type.",
                    "Target": "privateEndpointConnection"
                },
                {
                    "Id": "b2bf8c0d-27e1-11ec-9ce8-b357a2761d24",
                    "ApiChange": "Resource",
                    "ChangedApiName": "privateLinkPolicy",
                    "ChangeType": "Addition",
                    "Description": "Added the [privateLinkPolicy](https://docs.microsoft.com/en-us/graph/api/resources/privateLinkPolicy?view=graph-rest-beta) resource type.",
                    "Target": "privateLinkPolicy"
                },
                {
                    "Id": "b2c44ac0-27e1-11ec-9ce8-b357a2761d24",
                    "ApiChange": "Property",
                    "ChangedApiName": "squareDarkLogo",
                    "ChangeType": "Addition",
                    "Description": "Added the **squareDarkLogo** property to the [organizationalBrandingProperties](https://docs.microsoft.com/en-us/graph/api/resources/organizationalBrandingProperties?view=graph-rest-beta) resource.",
                    "Target": "organizationalBrandingProperties"
                },
                {
                    "Id": "b2c6aefc-27e1-11ec-9ce8-b357a2761d24",
                    "ApiChange": "Property",
                    "ChangedApiName": "squareDarkLogoRelativeUrl",
                    "ChangeType": "Addition",
                    "Description": "Added the **squareDarkLogoRelativeUrl** property to the [organizationalBrandingProperties](https://docs.microsoft.com/en-us/graph/api/resources/organizationalBrandingProperties?view=graph-rest-beta) resource.",
                    "Target": "organizationalBrandingProperties"
                },
                {
                    "Id": "b2c91291-27e1-11ec-9ce8-b357a2761d24",
                    "ApiChange": "Property",
                    "ChangedApiName": "certifiedApplicationsOnly",
                    "ChangeType": "Addition",
                    "Description": "Added the **certifiedApplicationsOnly** property to the [servicePrincipalCreationConditionSet](https://docs.microsoft.com/en-us/graph/api/resources/servicePrincipalCreationConditionSet?view=graph-rest-beta) resource.",
                    "Target": "servicePrincipalCreationConditionSet"
                },
                {
                    "Id": "b2cb72a3-27e1-11ec-9ce8-b357a2761d24",
                    "ApiChange": "Property",
                    "ChangedApiName": "certifiedClientApplicationsOnly",
                    "ChangeType": "Addition",
                    "Description": "Added the **certifiedClientApplicationsOnly** property to the [permissionGrantConditionSet](https://docs.microsoft.com/en-us/graph/api/resources/permissionGrantConditionSet?view=graph-rest-beta) resource.",
                    "Target": "permissionGrantConditionSet"
                },
                {
                    "Id": "b2cddd84-27e1-11ec-9ce8-b357a2761d24",
                    "ApiChange": "Relationship",
                    "ChangedApiName": "privateLinkPolicies",
                    "ChangeType": "Addition",
                    "Description": "Added the **privateLinkPolicies** relationship to the [policyRoot](https://docs.microsoft.com/en-us/graph/api/resources/policyRoot?view=graph-rest-beta) resource.",
                    "Target": "policyRoot"
                },
                {
                    "Id": "b2d0391d-27e1-11ec-9ce8-b357a2761d24",
                    "ApiChange": "Resource",
                    "ChangedApiName": "multiTenantCollaborationPendingMemberState",
                    "ChangeType": "Addition",
                    "Description": "Added the [multiTenantCollaborationPendingMemberState](https://docs.microsoft.com/en-us/graph/api/resources/multiTenantCollaborationPendingMemberState?view=graph-rest-beta) resource type.",
                    "Target": "multiTenantCollaborationPendingMemberState"
                },
                {
                    "Id": "b2d9ca5b-27e1-11ec-9ce8-b357a2761d24",
                    "ApiChange": "Property",
                    "ChangedApiName": "licenseMigrationInfo",
                    "ChangeType": "Addition",
                    "Description": "Added the **licenseMigrationInfo** property to the [organization](https://docs.microsoft.com/en-us/graph/api/resources/organization?view=graph-rest-beta) resource.",
                    "Target": "organization"
                },
                {
                    "Id": "b2e0eb7d-27e1-11ec-9ce8-b357a2761d24",
                    "ApiChange": "Property",
                    "ChangedApiName": "isMemberManagementRestricted",
                    "ChangeType": "Addition",
                    "Description": "Added the **isMemberManagementRestricted** property to the [administrativeUnit](https://docs.microsoft.com/en-us/graph/api/resources/administrativeUnit?view=graph-rest-beta) resource.",
                    "Target": "administrativeUnit"
                },
                {
                    "Id": "b2e34c54-27e1-11ec-9ce8-b357a2761d24",
                    "ApiChange": "Property",
                    "ChangedApiName": "membershipRule",
                    "ChangeType": "Addition",
                    "Description": "Added the **membershipRule** property to the [administrativeUnit](https://docs.microsoft.com/en-us/graph/api/resources/administrativeUnit?view=graph-rest-beta) resource.",
                    "Target": "administrativeUnit"
                },
                {
                    "Id": "b2e5ae5c-27e1-11ec-9ce8-b357a2761d24",
                    "ApiChange": "Property",
                    "ChangedApiName": "membershipType",
                    "ChangeType": "Addition",
                    "Description": "Added the **membershipType** property to the [administrativeUnit](https://docs.microsoft.com/en-us/graph/api/resources/administrativeUnit?view=graph-rest-beta) resource.",
                    "Target": "administrativeUnit"
                },
                {
                    "Id": "b2e81001-27e1-11ec-9ce8-b357a2761d24",
                    "ApiChange": "Property",
                    "ChangedApiName": "membershipRuleProcessingState",
                    "ChangeType": "Addition",
                    "Description": "Added the **membershipRuleProcessingState** property to the [administrativeUnit](https://docs.microsoft.com/en-us/graph/api/resources/administrativeUnit?view=graph-rest-beta) resource.",
                    "Target": "administrativeUnit"
                },
                {
                    "Id": "b2ea7560-27e1-11ec-9ce8-b357a2761d24",
                    "ApiChange": "Resource",
                    "ChangedApiName": "customSecurityAttributeValue",
                    "ChangeType": "Addition",
                    "Description": "Added the [customSecurityAttributeValue](https://docs.microsoft.com/en-us/graph/api/resources/customSecurityAttributeValue?view=graph-rest-beta) resource type.",
                    "Target": "customSecurityAttributeValue"
                },
                {
                    "Id": "b2ecd500-27e1-11ec-9ce8-b357a2761d24",
                    "ApiChange": "Relationship",
                    "ChangedApiName": "domainNameReferences",
                    "ChangeType": "Addition",
                    "Description": "Added the **domainNameReferences** relationship to the [sharedEmailDomain](https://docs.microsoft.com/en-us/graph/api/resources/sharedEmailDomain?view=graph-rest-beta) resource.",
                    "Target": "sharedEmailDomain"
                },
                {
                    "Id": "b2ef3791-27e1-11ec-9ce8-b357a2761d24",
                    "ApiChange": "Property",
                    "ChangedApiName": "allowedToReadBitlockerKeysForOwnedDevice",
                    "ChangeType": "Addition",
                    "Description": "Added the **allowedToReadBitlockerKeysForOwnedDevice** property to the [defaultUserRolePermissions](https://docs.microsoft.com/en-us/graph/api/resources/defaultUserRolePermissions?view=graph-rest-beta) resource.",
                    "Target": "defaultUserRolePermissions"
                },
                {
                    "Id": "b2f198f8-27e1-11ec-9ce8-b357a2761d24",
                    "ApiChange": "Property",
                    "ChangedApiName": "Status",
                    "ChangeType": "Addition",
                    "Description": "Added the **Status** property to the [domainState](https://docs.microsoft.com/en-us/graph/api/resources/domainState?view=graph-rest-beta) resource.",
                    "Target": "domainState"
                },
                {
                    "Id": "b2f3fc6f-27e1-11ec-9ce8-b357a2761d24",
                    "ApiChange": "Property",
                    "ChangedApiName": "LastActionDateTime",
                    "ChangeType": "Addition",
                    "Description": "Added the **LastActionDateTime** property to the [domainState](https://docs.microsoft.com/en-us/graph/api/resources/domainState?view=graph-rest-beta) resource.",
                    "Target": "domainState"
                },
                {
                    "Id": "b2f65dd7-27e1-11ec-9ce8-b357a2761d24",
                    "ApiChange": "Resource",
                    "ChangedApiName": "crossTenantAccessPolicyOutboundSetting",
                    "ChangeType": "Addition",
                    "Description": "Added the [crossTenantAccessPolicyOutboundSetting](https://docs.microsoft.com/en-us/graph/api/resources/crossTenantAccessPolicyOutboundSetting?view=graph-rest-beta) resource type.",
                    "Target": "crossTenantAccessPolicyOutboundSetting"
                },
                {
                    "Id": "b2f8c100-27e1-11ec-9ce8-b357a2761d24",
                    "ApiChange": "Resource",
                    "ChangedApiName": "crossTenantAccessPolicyInboundSetting",
                    "ChangeType": "Addition",
                    "Description": "Added the [crossTenantAccessPolicyInboundSetting](https://docs.microsoft.com/en-us/graph/api/resources/crossTenantAccessPolicyInboundSetting?view=graph-rest-beta) resource type.",
                    "Target": "crossTenantAccessPolicyInboundSetting"
                },
                {
                    "Id": "b2fb23d3-27e1-11ec-9ce8-b357a2761d24",
                    "ApiChange": "Resource",
                    "ChangedApiName": "inboundSharedUserProfile",
                    "ChangeType": "Addition",
                    "Description": "Added the [inboundSharedUserProfile](https://docs.microsoft.com/en-us/graph/api/resources/inboundSharedUserProfile?view=graph-rest-beta) resource type.",
                    "Target": "inboundSharedUserProfile"
                },
                {
                    "Id": "b2fd85e2-27e1-11ec-9ce8-b357a2761d24",
                    "ApiChange": "Resource",
                    "ChangedApiName": "tenantReference",
                    "ChangeType": "Addition",
                    "Description": "Added the [tenantReference](https://docs.microsoft.com/en-us/graph/api/resources/tenantReference?view=graph-rest-beta) resource type.",
                    "Target": "tenantReference"
                },
                {
                    "Id": "b2ffe7af-27e1-11ec-9ce8-b357a2761d24",
                    "ApiChange": "Resource",
                    "ChangedApiName": "outboundSharedUserProfile",
                    "ChangeType": "Addition",
                    "Description": "Added the [outboundSharedUserProfile](https://docs.microsoft.com/en-us/graph/api/resources/outboundSharedUserProfile?view=graph-rest-beta) resource type.",
                    "Target": "outboundSharedUserProfile"
                },
                {
                    "Id": "b3024b40-27e1-11ec-9ce8-b357a2761d24",
                    "ApiChange": "Resource",
                    "ChangedApiName": "complexExtensionValue",
                    "ChangeType": "Addition",
                    "Description": "Added the [complexExtensionValue](https://docs.microsoft.com/en-us/graph/api/resources/complexExtensionValue?view=graph-rest-beta) resource type.",
                    "Target": "complexExtensionValue"
                },
                {
                    "Id": "b304ac69-27e1-11ec-9ce8-b357a2761d24",
                    "ApiChange": "Resource",
                    "ChangedApiName": "passwordValidationInformation",
                    "ChangeType": "Addition",
                    "Description": "Added the [passwordValidationInformation](https://docs.microsoft.com/en-us/graph/api/resources/passwordValidationInformation?view=graph-rest-beta) resource type.",
                    "Target": "passwordValidationInformation"
                },
                {
                    "Id": "b30711d0-27e1-11ec-9ce8-b357a2761d24",
                    "ApiChange": "Resource",
                    "ChangedApiName": "requestSignatureVerification",
                    "ChangeType": "Addition",
                    "Description": "Added the [requestSignatureVerification](https://docs.microsoft.com/en-us/graph/api/resources/requestSignatureVerification?view=graph-rest-beta) resource type.",
                    "Target": "requestSignatureVerification"
                },
                {
                    "Id": "b30971b4-27e1-11ec-9ce8-b357a2761d24",
                    "ApiChange": "Resource",
                    "ChangedApiName": "validationResult",
                    "ChangeType": "Addition",
                    "Description": "Added the [validationResult](https://docs.microsoft.com/en-us/graph/api/resources/validationResult?view=graph-rest-beta) resource type.",
                    "Target": "validationResult"
                },
                {
                    "Id": "b30bd49f-27e1-11ec-9ce8-b357a2761d24",
                    "ApiChange": "Member",
                    "ChangedApiName": "unknown",
                    "ChangeType": "Addition",
                    "Description": "Added the `unknown` member to the **phoneType** enumeration.",
                    "Target": "phoneType"
                },
                {
                    "Id": "b30e3634-27e1-11ec-9ce8-b357a2761d24",
                    "ApiChange": "Member",
                    "ChangedApiName": "callback",
                    "ChangeType": "Addition",
                    "Description": "Added the `callback` member to the **phoneType** enumeration.",
                    "Target": "phoneType"
                },
                {
                    "Id": "b3109884-27e1-11ec-9ce8-b357a2761d24",
                    "ApiChange": "Member",
                    "ChangedApiName": "car",
                    "ChangeType": "Addition",
                    "Description": "Added the `car` member to the **phoneType** enumeration.",
                    "Target": "phoneType"
                },
                {
                    "Id": "b312fb23-27e1-11ec-9ce8-b357a2761d24",
                    "ApiChange": "Member",
                    "ChangedApiName": "primary",
                    "ChangeType": "Addition",
                    "Description": "Added the `primary` member to the **phoneType** enumeration.",
                    "Target": "phoneType"
                },
                {
                    "Id": "b3155c59-27e1-11ec-9ce8-b357a2761d24",
                    "ApiChange": "Member",
                    "ChangedApiName": "telex",
                    "ChangeType": "Addition",
                    "Description": "Added the `telex` member to the **phoneType** enumeration.",
                    "Target": "phoneType"
                },
                {
                    "Id": "b317c1f0-27e1-11ec-9ce8-b357a2761d24",
                    "ApiChange": "Member",
                    "ChangedApiName": "ttyTdd",
                    "ChangeType": "Addition",
                    "Description": "Added the `ttyTdd` member to the **phoneType** enumeration.",
                    "Target": "phoneType"
                },
                {
                    "Id": "b31a22dd-27e1-11ec-9ce8-b357a2761d24",
                    "ApiChange": "Member",
                    "ChangedApiName": "organizationMain",
                    "ChangeType": "Addition",
                    "Description": "Added the `organizationMain` member to the **phoneType** enumeration.",
                    "Target": "phoneType"
                },
                {
                    "Id": "b31c874c-27e1-11ec-9ce8-b357a2761d24",
                    "ApiChange": "Enum type",
                    "ChangedApiName": "weakAlgorithms",
                    "ChangeType": "Addition",
                    "Description": "Added the **weakAlgorithms** enumeration type.",
                    "Target": "weakAlgorithms"
                },
                {
                    "Id": "b3260cf3-27e1-11ec-9ce8-b357a2761d24",
                    "ApiChange": "Method",
                    "ChangedApiName": "delta",
                    "ChangeType": "Addition",
                    "Description": "Added the [delta](https://docs.microsoft.com/en-us/graph/api/directoryObject-delta?view=graph-rest-beta) method to the [directoryObject](https://docs.microsoft.com/en-us/graph/api/resources/directoryObject?view=graph-rest-beta) resource.",
                    "Target": "directoryObject"
                },
                {
                    "Id": "b32ad21c-27e1-11ec-9ce8-b357a2761d24",
                    "ApiChange": "Resource",
                    "ChangedApiName": "ComplexExtensionValue",
                    "ChangeType": "Deletion",
                    "Description": "Removed the **ComplexExtensionValue** resource type.",
                    "Target": "ComplexExtensionValue"
                },
                {
                    "Id": "b32d3502-27e1-11ec-9ce8-b357a2761d24",
                    "ApiChange": "Property",
                    "ChangedApiName": "status",
                    "ChangeType": "Deletion",
                    "Description": "Removed the **status** property from the [domainState](https://docs.microsoft.com/en-us/graph/api/resources/domainState?view=graph-rest-beta) resource.",
                    "Target": "domainState"
                },
                {
                    "Id": "b32f9745-27e1-11ec-9ce8-b357a2761d24",
                    "ApiChange": "Property",
                    "ChangedApiName": "lastActionDateTime",
                    "ChangeType": "Deletion",
                    "Description": "Removed the **lastActionDateTime** property from the [domainState](https://docs.microsoft.com/en-us/graph/api/resources/domainState?view=graph-rest-beta) resource.",
                    "Target": "domainState"
                },
                {
                    "Id": "b336c021-27e1-11ec-9ce8-b357a2761d24",
                    "ApiChange": "Member",
                    "ChangedApiName": "home",
                    "ChangeType": "Deletion",
                    "Description": "Removed the `home` member from the **phoneType** enumeration.",
                    "Target": "phoneType"
                },
                {
                    "Id": "b339217d-27e1-11ec-9ce8-b357a2761d24",
                    "ApiChange": "Member",
                    "ChangedApiName": "business",
                    "ChangeType": "Deletion",
                    "Description": "Removed the `business` member from the **phoneType** enumeration.",
                    "Target": "phoneType"
                },
                {
                    "Id": "b33b852d-27e1-11ec-9ce8-b357a2761d24",
                    "ApiChange": "Member",
                    "ChangedApiName": "mobile",
                    "ChangeType": "Deletion",
                    "Description": "Removed the `mobile` member from the **phoneType** enumeration.",
                    "Target": "phoneType"
                },
                {
                    "Id": "b33de8d9-27e1-11ec-9ce8-b357a2761d24",
                    "ApiChange": "Member",
                    "ChangedApiName": "other",
                    "ChangeType": "Deletion",
                    "Description": "Removed the `other` member from the **phoneType** enumeration.",
                    "Target": "phoneType"
                },
                {
                    "Id": "b340462c-27e1-11ec-9ce8-b357a2761d24",
                    "ApiChange": "Member",
                    "ChangedApiName": "assistant",
                    "ChangeType": "Deletion",
                    "Description": "Removed the `assistant` member from the **phoneType** enumeration.",
                    "Target": "phoneType"
                },
                {
                    "Id": "b342a9a9-27e1-11ec-9ce8-b357a2761d24",
                    "ApiChange": "Member",
                    "ChangedApiName": "homeFax",
                    "ChangeType": "Deletion",
                    "Description": "Removed the `homeFax` member from the **phoneType** enumeration.",
                    "Target": "phoneType"
                },
                {
                    "Id": "b3450efb-27e1-11ec-9ce8-b357a2761d24",
                    "ApiChange": "Member",
                    "ChangedApiName": "businessFax",
                    "ChangeType": "Deletion",
                    "Description": "Removed the `businessFax` member from the **phoneType** enumeration.",
                    "Target": "phoneType"
                },
                {
                    "Id": "b3476fe4-27e1-11ec-9ce8-b357a2761d24",
                    "ApiChange": "Member",
                    "ChangedApiName": "otherFax",
                    "ChangeType": "Deletion",
                    "Description": "Removed the `otherFax` member from the **phoneType** enumeration.",
                    "Target": "phoneType"
                },
                {
                    "Id": "b349d47b-27e1-11ec-9ce8-b357a2761d24",
                    "ApiChange": "Member",
                    "ChangedApiName": "pager",
                    "ChangeType": "Deletion",
                    "Description": "Removed the `pager` member from the **phoneType** enumeration.",
                    "Target": "phoneType"
                },
                {
                    "Id": "b34c32df-27e1-11ec-9ce8-b357a2761d24",
                    "ApiChange": "Member",
                    "ChangedApiName": "radio",
                    "ChangeType": "Deletion",
                    "Description": "Removed the `radio` member from the **phoneType** enumeration.",
                    "Target": "phoneType"
                },
                {
                    "Id": "b34e9689-27e1-11ec-9ce8-b357a2761d24",
                    "ApiChange": "Method",
                    "ChangedApiName": "activateService",
                    "ChangeType": "Deletion",
                    "Description": "Removed the **activateService** method from the [organization](https://docs.microsoft.com/en-us/graph/api/resources/organization?view=graph-rest-beta) resource.",
                    "Target": "organization"
                }
            ],
            "Id": "b28eb8c8-27e1-11ec-9ce8-b357a2761d24",
            "Cloud": "prd",
            "Version": "beta",
            "CreatedDateTime": "2021-10-08T02:44:45.846Z",
            "WorkloadArea": "Identity and access",
            "SubArea": "Directory management"
        },
        {
            "ChangeList": [
                {
                    "Id": "b29aa396-27e1-11ec-9ce8-b357a2761d24",
                    "ApiChange": "Property",
                    "ChangedApiName": "isMultiValued",
                    "ChangeType": "Addition",
                    "Description": "Added the **isMultiValued** property to the [extensionProperty](https://docs.microsoft.com/en-us/graph/api/resources/extensionProperty?view=graph-rest-beta) resource.",
                    "Target": "extensionProperty"
                }
            ],
            "Id": "b28eb8c8-27e1-11ec-9ce8-b357a2761d24",
            "Cloud": "prd",
            "Version": "beta",
            "CreatedDateTime": "2021-10-08T02:44:45.846Z",
            "WorkloadArea": "Applications",
            "SubArea": ""
        },
        {
            "ChangeList": [
                {
                    "Id": "b29d0489-27e1-11ec-9ce8-b357a2761d24",
                    "ApiChange": "Property",
                    "ChangedApiName": "isManagementRestricted",
                    "ChangeType": "Addition",
                    "Description": "Added the **isManagementRestricted** property to the [application](https://docs.microsoft.com/en-us/graph/api/resources/application?view=graph-rest-beta) resource.",
                    "Target": "application"
                },
                {
                    "Id": "b29f6707-27e1-11ec-9ce8-b357a2761d24",
                    "ApiChange": "Relationship",
                    "ChangedApiName": "memberOf",
                    "ChangeType": "Addition",
                    "Description": "Added the **memberOf** relationship to the [application](https://docs.microsoft.com/en-us/graph/api/resources/application?view=graph-rest-beta) resource.",
                    "Target": "application"
                },
                {
                    "Id": "b2a1ca1c-27e1-11ec-9ce8-b357a2761d24",
                    "ApiChange": "Property",
                    "ChangedApiName": "oauth2RequirePostResponse",
                    "ChangeType": "Addition",
                    "Description": "Added the **oauth2RequirePostResponse** property to the [application](https://docs.microsoft.com/en-us/graph/api/resources/application?view=graph-rest-beta) resource.",
                    "Target": "application"
                },
                {
                    "Id": "b2a42ee8-27e1-11ec-9ce8-b357a2761d24",
                    "ApiChange": "Property",
                    "ChangedApiName": "requestSignatureVerification",
                    "ChangeType": "Addition",
                    "Description": "Added the **requestSignatureVerification** property to the [application](https://docs.microsoft.com/en-us/graph/api/resources/application?view=graph-rest-beta) resource.",
                    "Target": "application"
                },
                {
                    "Id": "b2a69307-27e1-11ec-9ce8-b357a2761d24",
                    "ApiChange": "Relationship",
                    "ChangedApiName": "claimsMappingPolicies",
                    "ChangeType": "Addition",
                    "Description": "Added the **claimsMappingPolicies** relationship to the [application](https://docs.microsoft.com/en-us/graph/api/resources/application?view=graph-rest-beta) resource.",
                    "Target": "application"
                }
            ],
            "Id": "b28eb8c8-27e1-11ec-9ce8-b357a2761d24",
            "Cloud": "prd",
            "Version": "beta",
            "CreatedDateTime": "2021-10-08T02:44:45.846Z",
            "WorkloadArea": "Applications",
            "SubArea": ""
        },
        {
            "ChangeList": [
                {
                    "Id": "b2a8f34c-27e1-11ec-9ce8-b357a2761d24",
                    "ApiChange": "Property",
                    "ChangedApiName": "createdDateTime",
                    "ChangeType": "Addition",
                    "Description": "Added the **createdDateTime** property to the [appRoleAssignment](https://docs.microsoft.com/en-us/graph/api/resources/appRoleAssignment?view=graph-rest-beta) resource.",
                    "Target": "appRoleAssignment"
                },
                {
                    "Id": "b2ab5604-27e1-11ec-9ce8-b357a2761d24",
                    "ApiChange": "Property",
                    "ChangedApiName": "lastModifiedDateTime",
                    "ChangeType": "Addition",
                    "Description": "Added the **lastModifiedDateTime** property to the [appRoleAssignment](https://docs.microsoft.com/en-us/graph/api/resources/appRoleAssignment?view=graph-rest-beta) resource.",
                    "Target": "appRoleAssignment"
                }
            ],
            "Id": "b28eb8c8-27e1-11ec-9ce8-b357a2761d24",
            "Cloud": "prd",
            "Version": "beta",
            "CreatedDateTime": "2021-10-08T02:44:45.846Z",
            "WorkloadArea": "Applications",
            "SubArea": ""
        },
        {
            "ChangeList": [
                {
                    "Id": "b2c1ecff-27e1-11ec-9ce8-b357a2761d24",
                    "ApiChange": "Property",
                    "ChangedApiName": "isManagementRestricted",
                    "ChangeType": "Addition",
                    "Description": "Added the **isManagementRestricted** property to the [group](https://docs.microsoft.com/en-us/graph/api/resources/group?view=graph-rest-beta) resource.",
                    "Target": "group"
                },
                {
                    "Id": "b31ee6c8-27e1-11ec-9ce8-b357a2761d24",
                    "ApiChange": "Method",
                    "ChangedApiName": "reprocessLicenseAssignment",
                    "ChangeType": "Addition",
                    "Description": "Added the [reprocessLicenseAssignment](https://docs.microsoft.com/en-us/graph/api/group-reprocessLicenseAssignment?view=graph-rest-beta) method to the [group](https://docs.microsoft.com/en-us/graph/api/resources/group?view=graph-rest-beta) resource.",
                    "Target": "group"
                },
                {
                    "Id": "b323ab94-27e1-11ec-9ce8-b357a2761d24",
                    "ApiChange": "Method",
                    "ChangedApiName": "renew",
                    "ChangeType": "Addition",
                    "Description": "Added the [renew](https://docs.microsoft.com/en-us/graph/api/group-renew?view=graph-rest-beta) method to the [group](https://docs.microsoft.com/en-us/graph/api/resources/group?view=graph-rest-beta) resource.",
                    "Target": "group"
                }
            ],
            "Id": "b28eb8c8-27e1-11ec-9ce8-b357a2761d24",
            "Cloud": "prd",
            "Version": "beta",
            "CreatedDateTime": "2021-10-08T02:44:45.846Z",
            "WorkloadArea": "Groups",
            "SubArea": ""
        },
        {
            "ChangeList": [
                {
                    "Id": "b2d29a50-27e1-11ec-9ce8-b357a2761d24",
                    "ApiChange": "Property",
                    "ChangedApiName": "customSecurityAttributes",
                    "ChangeType": "Addition",
                    "Description": "Added the **customSecurityAttributes** property to the [servicePrincipal](https://docs.microsoft.com/en-us/graph/api/resources/servicePrincipal?view=graph-rest-beta) resource.",
                    "Target": "servicePrincipal"
                },
                {
                    "Id": "b2d4fcd1-27e1-11ec-9ce8-b357a2761d24",
                    "ApiChange": "Property",
                    "ChangedApiName": "isManagementRestricted",
                    "ChangeType": "Addition",
                    "Description": "Added the **isManagementRestricted** property to the [servicePrincipal](https://docs.microsoft.com/en-us/graph/api/resources/servicePrincipal?view=graph-rest-beta) resource.",
                    "Target": "servicePrincipal"
                },
                {
                    "Id": "b2d75fd6-27e1-11ec-9ce8-b357a2761d24",
                    "ApiChange": "Property",
                    "ChangedApiName": "createdDateTime",
                    "ChangeType": "Addition",
                    "Description": "Added the **createdDateTime** property to the [servicePrincipal](https://docs.microsoft.com/en-us/graph/api/resources/servicePrincipal?view=graph-rest-beta) resource.",
                    "Target": "servicePrincipal"
                }
            ],
            "Id": "b28eb8c8-27e1-11ec-9ce8-b357a2761d24",
            "Cloud": "prd",
            "Version": "beta",
            "CreatedDateTime": "2021-10-08T02:44:45.846Z",
            "WorkloadArea": "Applications",
            "SubArea": ""
        },
        {
            "ChangeList": [
                {
                    "Id": "b2dc24f1-27e1-11ec-9ce8-b357a2761d24",
                    "ApiChange": "Property",
                    "ChangedApiName": "customSecurityAttributes",
                    "ChangeType": "Addition",
                    "Description": "Added the **customSecurityAttributes** property to the [user](https://docs.microsoft.com/en-us/graph/api/resources/user?view=graph-rest-beta) resource.",
                    "Target": "user"
                },
                {
                    "Id": "b2de89b1-27e1-11ec-9ce8-b357a2761d24",
                    "ApiChange": "Property",
                    "ChangedApiName": "isManagementRestricted",
                    "ChangeType": "Addition",
                    "Description": "Added the **isManagementRestricted** property to the [user](https://docs.microsoft.com/en-us/graph/api/resources/user?view=graph-rest-beta) resource.",
                    "Target": "user"
                },
                {
                    "Id": "b321498f-27e1-11ec-9ce8-b357a2761d24",
                    "ApiChange": "Method",
                    "ChangedApiName": "validatePassword",
                    "ChangeType": "Addition",
                    "Description": "Added the [validatePassword](https://docs.microsoft.com/en-us/graph/api/user-validatePassword?view=graph-rest-beta) method to the [user](https://docs.microsoft.com/en-us/graph/api/resources/user?view=graph-rest-beta) resource.",
                    "Target": "user"
                },
                {
                    "Id": "b3286db0-27e1-11ec-9ce8-b357a2761d24",
                    "ApiChange": "Relationship",
                    "ChangedApiName": "oauth2PermissionGrants",
                    "ChangeType": "Deletion",
                    "Description": "Removed the **oauth2PermissionGrants** relationship from the [user](https://docs.microsoft.com/en-us/graph/api/resources/user?view=graph-rest-beta) resource.",
                    "Target": "user"
                },
                {
                    "Id": "b350f643-27e1-11ec-9ce8-b357a2761d24",
                    "ApiChange": "Method",
                    "ChangedApiName": "activateServicePlan",
                    "ChangeType": "Deletion",
                    "Description": "Removed the **activateServicePlan** method from the [user](https://docs.microsoft.com/en-us/graph/api/resources/user?view=graph-rest-beta) resource.",
                    "Target": "user"
                }
            ],
            "Id": "b28eb8c8-27e1-11ec-9ce8-b357a2761d24",
            "Cloud": "prd",
            "Version": "beta",
            "CreatedDateTime": "2021-10-08T02:44:45.846Z",
            "WorkloadArea": "Users",
            "SubArea": ""
        },
        {
            "ChangeList": [
                {
                    "Id": "b331f95f-27e1-11ec-9ce8-b357a2761d24",
                    "ApiChange": "Property",
                    "ChangedApiName": "appId",
                    "ChangeType": "Change",
                    "Description": "Changed the **appId** property in the [preAuthorizedApplication](https://docs.microsoft.com/en-us/graph/api/resources/preAuthorizedApplication?view=graph-rest-beta) resource from required to optional.",
                    "Target": "preAuthorizedApplication"
                }
            ],
            "Id": "b28eb8c8-27e1-11ec-9ce8-b357a2761d24",
            "Cloud": "prd",
            "Version": "beta",
            "CreatedDateTime": "2021-10-08T02:44:45.846Z",
            "WorkloadArea": "Applications",
            "SubArea": ""
        },
        {
            "ChangeList": [
                {
                    "Id": "b3345ab3-27e1-11ec-9ce8-b357a2761d24",
                    "ApiChange": "Property",
                    "ChangedApiName": "forceChangePasswordNextSignInWithMfa",
                    "ChangeType": "Deletion",
                    "Description": "Removed the **forceChangePasswordNextSignInWithMfa** property from the [passwordProfile](https://docs.microsoft.com/en-us/graph/api/resources/passwordProfile?view=graph-rest-beta) resource.",
                    "Target": "passwordProfile"
                }
            ],
            "Id": "b28eb8c8-27e1-11ec-9ce8-b357a2761d24",
            "Cloud": "prd",
            "Version": "beta",
            "CreatedDateTime": "2021-10-08T02:44:45.846Z",
            "WorkloadArea": "Users",
            "SubArea": ""
        }
    ]
}